<?xml version="1.0" encoding="UTF-8"?><?xml-model href="https://rawgit.com/OpenArabicPE/OpenArabicPE_ODD/v0.1/schema/tei_periodical.rng" type="application/xml" schematypens="http://relaxng.org/ns/structure/1.0"?><?xml-stylesheet type="text/xsl" href="../xslt-boilerplate/teibp_parameters.xsl"?><tei:TEI xmlns:tei="http://www.tei-c.org/ns/1.0"
         xmlns="http://www.tei-c.org/ns/1.0"
         xml:id="oclc_792755216-i_100"
         prev="oclc_792755216-i_99"
         next="oclc_792755216-i_101">
   <tei:teiHeader xml:lang="en">
      <tei:fileDesc>
         <tei:titleStmt>
            <title>Thamarāt al-Funūn #100, 22 March 1877</title>
            <title type="sub">TEI edition</title>
            <respStmt xml:lang="en">
               <resp>TEI edition</resp>
               <persName xml:id="pers_TG">Till Grallert</persName>
            </respStmt>
         </tei:titleStmt>
         <tei:publicationStmt>
            <authority>
               <persName>Till Grallert</persName>
            </authority>
            <pubPlace>Beirut</pubPlace>
            <date when="2017">2017</date>
            <availability status="restricted">
               <licence target="http://creativecommons.org/licenses/by-sa/4.0/">Distributed under a Creative Commons Attribution-ShareAlike 4.0 International (CC BY-SA 4.0) license</licence>
            </availability>
            <idno type="url">https://github.com/openarabicpe/newspaper_thamarat-al-funun/blob/master/xml/oclc_792755216-i_100.TEIP5.xml</idno>
         </tei:publicationStmt>
         <tei:sourceDesc>
            <tei:biblStruct xml:lang="en" xml:id="biblStruct_2.d1e11359">
               <tei:monogr xml:lang="en" xml:id="monogr_2.d1e11361">
                  <title level="j" xml:lang="ar" xml:id="title_602.d1e11363">ثمرات الفنون</title>
                  <title level="j" type="sub" xml:lang="ar" xml:id="title_603.d1e11366">ان هذه الصحيفة على حوادث سياسية ومحلية وتجارة وفنون</title>
                  <title level="j" type="sub" xml:lang="ar" xml:id="title_604.d1e11369">صدورها في يوم الخميس من كل اسبوع</title>
                  <title level="j" xml:lang="ar-Latn-x-ijmes" xml:id="title_605.d1e11372">Thamarāt al-Funūn</title>
                  <title level="j"
                         type="sub"
                         xml:lang="ar-Latn-x-ijmes"
                         xml:id="title_606.d1e11375">Inna hadhihi al-ṣaḥīfa ʿalā ḥawādith siyāsiyya wa-maḥalliyya wa-tijāra wa-funūn</title>
                  <title level="j"
                         type="sub"
                         xml:lang="ar-Latn-x-ijmes"
                         xml:id="title_607.d1e11379">ṣudūruhā fī yawm al-khamīs min kull usbūʿ</title>
                  <idno type="oclc" xml:lang="en" xml:id="idno_601.d1e11382">792755216</idno>
                  <idno type="oclc" xml:lang="en" xml:id="idno_602.d1e11385">745202659</idno>
                  <idno type="oclc" xml:lang="en" xml:id="idno_603.d1e11388">915538205</idno>
                  <idno type="oclc" xml:lang="en" xml:id="idno_604.d1e11391">30431084</idno>
                  <idno type="oclc" xml:lang="en" xml:id="idno_605.d1e11394">499946128</idno>
                  <idno type="oclc" xml:lang="en" xml:id="idno_606.d1e11398">177646790</idno>
                  <editor xml:lang="en" xml:id="editor_101.d1e11401">
                     <persName xml:lang="ar" xml:id="persName_201.d1e11403">
                        <forename xml:id="forename_201.d1e11405">عبد القادر</forename>
                        <surname xml:id="surname_201.d1e11408">قباني</surname>
                     </persName>
                     <persName xml:lang="ar-Latn-x-ijmes" xml:id="persName_202.d1e11412">
                        <forename xml:id="forename_202.d1e11414">ʿAbd al-Qādir</forename>
                        <surname xml:id="surname_202.d1e11417">Qabbānī</surname>
                     </persName>
                  </editor>
                  <tei:imprint xml:lang="en" xml:id="imprint_2.d1e11422">
                     <publisher xml:lang="en" xml:id="publisher_101.d1e11424">
                        <orgName xml:lang="ar" xml:id="orgName_201.d1e11426">مطبعة جمعية الفنون</orgName>
                        <orgName xml:lang="ar-Latn-x-ijmes" xml:id="orgName_202.d1e11429">Maṭbaʿa Jamʿiyyat al-Funūn</orgName>
                     </publisher>
                     <pubPlace xml:lang="en" xml:id="pubPlace_101.d1e11433">
                        <placeName xml:lang="ar" xml:id="placeName_401.d1e11435">بيروت</placeName>
                        <placeName xml:lang="ar-Latn-x-ijmes" xml:id="placeName_402.d1e11438">Bayrūt</placeName>
                        <placeName xml:lang="en" xml:id="placeName_403.d1e11441">Beirut</placeName>
                        <placeName xml:lang="fr" xml:id="placeName_404.d1e11444">Beyrouth</placeName>
                     </pubPlace>
                     <tei:date type="official"
                               when="1877-03-22"
                               datingMethod="#cal_gregorian"
                               calendar="#cal_gregorian"
                               xml:lang="ar-Latn-x-ijmes"
                               xml:id="date_3.d1e11448">22 March 1877</tei:date>
                     <tei:date type="computed"
                               when="1877-03-22"
                               datingMethod="#cal_islamic"
                               calendar="#cal_islamic"
                               when-custom="1294-03-07"
                               xml:lang="ar-Latn-x-ijmes"
                               xml:id="date_3.d1e11451">7 Rabīʿ al-awwal 1294</tei:date>
                     <tei:date type="official"
                               when="1877-03-22"
                               datingMethod="#cal_julian"
                               calendar="#cal_julian"
                               when-custom="1877-03-10"
                               xml:lang="ar-Latn-x-ijmes"
                               xml:id="date_3.d1e11454">10 Ādhār 1877</tei:date>
                  </tei:imprint>
                  <tei:biblScope from="2" to="2" unit="volume" xml:id="biblScope_103.d1e11458"/>
                  <tei:biblScope from="100"
                                 to="100"
                                 unit="issue"
                                 xml:id="biblScope_103.d1e11460"/>
                  <biblScope from="1" to="4" unit="page" xml:id="biblScope_103.d1e11462"/>
               </tei:monogr>
               <note n="p_weekdays-published" type="param" xml:id="note_201.d1e11465">Thursday</note>
               <note n="p_step" type="param" xml:id="note_202.d1e11468">daily</note>
            </tei:biblStruct>
         </tei:sourceDesc>
      </tei:fileDesc>
      <tei:revisionDesc>
         <tei:change when="2017-11-06">Created this file by automatic conversion of <tei:gi>biblStruct</tei:gi> from file:/BachUni/BachBibliothek/GitHub/OpenArabicPE/newspaper_thamarat-al-funun/metadata/thamarat-al-funun.TEIP5.xml.</tei:change>
      </tei:revisionDesc>
   </tei:teiHeader>
   <tei:facsimile>
      <tei:surface xml:id="facs_1"/>
      <tei:surface xml:id="facs_2"/>
      <tei:surface xml:id="facs_3"/>
      <tei:surface xml:id="facs_4"/>
   </tei:facsimile>
   <tei:text xml:lang="ar">
      <tei:pb ed="print" n="1" facs="#facs_1"/>
      <tei:body>
         <tei:pb ed="print" n="2" facs="#facs_2"/>
         <tei:pb ed="print" n="3" facs="#facs_3"/>
         <tei:pb ed="print" n="4" facs="#facs_4"/>
      </tei:body>
   </tei:text>
</tei:TEI>
