<?xml version="1.0" encoding="UTF-8"?><?xml-model href="https://rawgit.com/OpenArabicPE/OpenArabicPE_ODD/master/schema/tei_periodical.rng" type="application/xml" schematypens="http://relaxng.org/ns/structure/1.0"?><?xml-model href="https://rawgit.com/OpenArabicPE/OpenArabicPE_ODD/master/schema/tei_periodical.rng" type="application/xml" schematypens="http://purl.oclc.org/dsdl/schematron"?><?xml-model href="https://rawgit.com/OpenArabicPE/OpenArabicPE_ODD/master/schema/tei_periodical.sch" type="application/xml" schematypens="http://purl.oclc.org/dsdl/schematron"?><?xml-stylesheet type="text/xsl" href="../boilerplate/xslt/teibp_parameters.xsl"?><tei:TEI xmlns:tei="http://www.tei-c.org/ns/1.0" xmlns="http://www.tei-c.org/ns/1.0" xml:id="oclc_792755216-i_381" prev="oclc_792755216-i_380.TEIP5.xml" next="oclc_792755216-i_382.TEIP5.xml">
   <tei:teiHeader xml:lang="en" change="#d2e172" xml:id="teiHeader_1.d2e7">
      <tei:fileDesc change="#d2e172" xml:id="fileDesc_1.d2e9">
         <tei:titleStmt change="#d2e172" xml:id="titleStmt_1.d2e11">
            <title change="#d2e172" xml:id="title_1.d2e13">Thamarāt al-Funūn #381, 15 May 1882</title>
            <title type="sub" change="#d2e172" xml:id="title_2.d2e16">TEI edition</title>
            <respStmt xml:lang="en" change="#d2e172" xml:id="respStmt_1.d2e19">
               <resp change="#d2e172" xml:id="resp_1.d2e21">TEI edition</resp>
               <persName xml:id="pers_TG">Till Grallert</persName>
            </respStmt>
         </tei:titleStmt>
         <tei:publicationStmt change="#d2e172" xml:id="publicationStmt_1.d2e29">
            <authority change="#d2e172" xml:id="authority_1.d2e31">
               <persName change="#d2e172" xml:id="persName_2.d2e33">Till Grallert</persName>
            </authority>
            <pubPlace change="#d2e172" xml:id="pubPlace_1.d2e37">Beirut</pubPlace>
            <date when="2018" change="#d2e172" xml:id="date_1.d2e40">2018</date>
            <availability status="restricted" change="#d2e172" xml:id="availability_1.d2e43">
               <licence target="http://creativecommons.org/licenses/by-sa/4.0/" change="#d2e172" xml:id="licence_1.d2e45">Distributed under a Creative Commons Attribution-ShareAlike 4.0 International (CC BY-SA 4.0) license</licence>
            </availability>
            <idno type="url" change="#d2e172" xml:id="idno_1.d2e49">https://github.com/openarabicpe/newspaper_thamarat-al-funun/blob/master/xml/oclc_792755216-i_381.TEIP5.xml</idno>
         </tei:publicationStmt>
         <tei:sourceDesc change="#d2e172" xml:id="sourceDesc_1.d2e53">
            <tei:biblStruct xml:id="biblStruct_2.d1e43202" xml:lang="en">
                    <tei:monogr xml:id="monogr_2.d1e43204" xml:lang="en">
                        <title level="j" xml:id="title_2288.d1e43206" xml:lang="ar">ثمرات الفنون</title>
                        <title level="j" type="sub" xml:id="title_2289.d1e43209" xml:lang="ar">ان هذه الصحيفة تحتوي على حوادث سياسية ومحلية وتجارية وفنون</title>
                        <title level="j" type="sub" xml:id="title_2290.d1e43212" xml:lang="ar">صدورها في يوم الاثنين من كل اسبوع</title>
                        <title level="j" xml:id="title_2291.d1e43215" xml:lang="ar-Latn-x-ijmes">Thamarāt al-Funūn</title>
                        <title level="j" type="sub" xml:id="title_2292.d1e43218" xml:lang="ar-Latn-x-ijmes">Inna hadhihi al-ṣaḥīfa taḥtawī ʿalā ḥawādith siyāsiyya wa-maḥalliyya wa-tijāriyya wa-funūn</title>
                        <title level="j" type="sub" xml:id="title_2293.d1e43222" xml:lang="ar-Latn-x-ijmes">ṣudūruhā fī yawm al-ithnayn min kull usbūʿ</title>
                        <idno type="oclc" xml:id="idno_2287.d1e43225" xml:lang="en">792755216</idno>
                        <idno type="oclc" xml:id="idno_2288.d1e43228" xml:lang="en">745202659</idno>
                        <idno type="oclc" xml:id="idno_2289.d1e43231" xml:lang="en">915538205</idno>
                        <idno type="oclc" xml:id="idno_2290.d1e43234" xml:lang="en">30431084</idno>
                        <idno type="oclc" xml:id="idno_2291.d1e43237" xml:lang="en">499946128</idno>
                        <idno type="oclc" xml:id="idno_2292.d1e43241" xml:lang="en">177646790</idno>
                        <editor xml:id="editor_382.d1e43244" xml:lang="en">
                            <persName xml:id="persName_763.d1e43246" xml:lang="ar">
                                <forename xml:id="forename_763.d1e43248">عبد القادر</forename>
                                <surname xml:id="surname_763.d1e43251">قباني</surname>
                            </persName>
                            <persName xml:id="persName_764.d1e43255" xml:lang="ar-Latn-x-ijmes">
                                <forename xml:id="forename_764.d1e43257">ʿAbd al-Qādir</forename>
                                <surname xml:id="surname_764.d1e43260">Qabbānī</surname>
                            </persName>
                        </editor>
                        <tei:imprint xml:id="imprint_2.d1e43265" xml:lang="en">
                            <publisher xml:id="publisher_382.d1e43267" xml:lang="en">
                                <orgName xml:id="orgName_763.d1e43269" xml:lang="ar">مطبعة جمعية الفنون</orgName>
                                <orgName xml:id="orgName_764.d1e43272" xml:lang="ar-Latn-x-ijmes">Maṭbaʿa Jamʿiyyat al-Funūn</orgName>
                            </publisher>
                            <pubPlace xml:id="pubPlace_382.d1e43276" xml:lang="en">
                                <placeName xml:id="placeName_1525.d1e43278" xml:lang="ar">بيروت</placeName>
                                <placeName xml:id="placeName_1526.d1e43281" xml:lang="ar-Latn-x-ijmes">Bayrūt</placeName>
                                <placeName xml:id="placeName_1527.d1e43284" xml:lang="en">Beirut</placeName>
                                <placeName xml:id="placeName_1528.d1e43287" xml:lang="fr">Beyrouth</placeName>
                            </pubPlace>
                            <tei:date calendar="#cal_gregorian" datingMethod="#cal_gregorian" type="official" when="1882-05-15" xml:id="date_3.d1e43291" xml:lang="ar-Latn-x-ijmes">15 May 1882</tei:date>
                            <tei:date calendar="#cal_islamic" datingMethod="#cal_islamic" type="computed" when="1882-05-15" when-custom="1299-06-26" xml:id="date_3.d1e43294" xml:lang="ar-Latn-x-ijmes">26 Jumāda al-tāniya 1299</tei:date>
                            <tei:date calendar="#cal_julian" datingMethod="#cal_julian" type="official" when="1882-05-15" when-custom="1882-05-03" xml:id="date_3.d1e43297" xml:lang="ar-Latn-x-ijmes">3 Ayyār 1882</tei:date>
                        </tei:imprint>
                        <tei:biblScope from="8" to="8" unit="volume" xml:id="biblScope_384.d1e43301"/>
                        <tei:biblScope from="381" to="381" unit="issue" xml:id="biblScope_384.d1e43303"/>
                        <biblScope from="1" to="4" unit="page" xml:id="biblScope_384.d1e43305"/>
                    </tei:monogr>
                    <note n="p_weekdays-published" type="param" xml:id="note_763.d1e43308">Monday</note>
                    <note n="p_step" type="param" xml:id="note_764.d1e43311">daily</note>
                </tei:biblStruct>
         </tei:sourceDesc>
      </tei:fileDesc>
      <tei:revisionDesc><change when="2018-07-09" who="#pers_TG" xml:id="d2e172" xml:lang="en">Added automated <tei:att xml:lang="en">xml:id</tei:att>s for every element that is a descendant of <tei:gi xml:lang="en">tei:text</tei:gi> and had no existing <tei:att xml:lang="en">xml:id</tei:att> following the pattern "name()_generate-id()".</change>
         <tei:change when="2018-07-04" change="#d2e172" xml:id="change_1.d2e172">Created this file by automatic conversion of <tei:gi change="#d2e172" xml:id="gi_1.d2e174">biblStruct</tei:gi> from file:/BachUni/BachBibliothek/GitHub/OpenArabicPE/newspaper_thamarat-al-funun/metadata/thamarat-al-funun.TEIP5.xml.</tei:change>
      </tei:revisionDesc>
   </tei:teiHeader>
   <tei:facsimile change="#d2e172" xml:id="facsimile_1.d2e180">
      <tei:surface xml:id="facs_1">
         <tei:graphic xml:id="facs_1-g_1" url="../images/issues/oclc_792755216-i_381-p_1.jpg" mimeType="image/jpeg"/>
      </tei:surface>
      <tei:surface xml:id="facs_2">
         <tei:graphic xml:id="facs_2-g_1" url="../images/issues/oclc_792755216-i_381-p_2.jpg" mimeType="image/jpeg"/>
      </tei:surface>
      <tei:surface xml:id="facs_3">
         <tei:graphic xml:id="facs_3-g_1" url="../images/issues/oclc_792755216-i_381-p_3.jpg" mimeType="image/jpeg"/>
      </tei:surface>
      <tei:surface xml:id="facs_4">
         <tei:graphic xml:id="facs_4-g_1" url="../images/issues/oclc_792755216-i_381-p_4.jpg" mimeType="image/jpeg"/>
      </tei:surface>
   </tei:facsimile>
   <tei:text xml:lang="ar" change="#d2e172" xml:id="text_1.d2e203">
      <tei:pb ed="print" n="1" facs="#facs_1" change="#d2e172" xml:id="pb_1.d2e205"/>
      <tei:body change="#d2e172" xml:id="body_1.d2e207">
         <tei:div type="item" change="#d2e172" xml:id="div_1.d2e209"/>
         <tei:pb ed="print" n="2" facs="#facs_2" change="#d2e172" xml:id="pb_1.d2e211"/>
         <tei:pb ed="print" n="3" facs="#facs_3" change="#d2e172" xml:id="pb_1.d2e213"/>
         <tei:pb ed="print" n="4" facs="#facs_4" change="#d2e172" xml:id="pb_1.d2e215"/>
      </tei:body>
   </tei:text>
</tei:TEI>