<?xml version="1.0" encoding="UTF-8"?><?xml-model href="https://rawgit.com/OpenArabicPE/OpenArabicPE_ODD/master/schema/tei_periodical.rng" type="application/xml" schematypens="http://relaxng.org/ns/structure/1.0"?><?xml-model href="https://rawgit.com/OpenArabicPE/OpenArabicPE_ODD/master/schema/tei_periodical.rng" type="application/xml" schematypens="http://purl.oclc.org/dsdl/schematron"?><?xml-model href="https://rawgit.com/OpenArabicPE/OpenArabicPE_ODD/master/schema/tei_periodical.sch" type="application/xml" schematypens="http://purl.oclc.org/dsdl/schematron"?><?xml-stylesheet type="text/xsl" href="../boilerplate/xslt/teibp_parameters.xsl"?><tei:TEI xmlns:tei="http://www.tei-c.org/ns/1.0"
         xmlns="http://www.tei-c.org/ns/1.0"
         xml:id="oclc_792755216-i_360"
         prev="oclc_792755216-i_359.TEIP5.xml"
         next="oclc_792755216-i_361.TEIP5.xml">
   <tei:teiHeader xml:lang="en">
      <tei:fileDesc>
         <tei:titleStmt>
            <title>Thamarāt al-Funūn #360, 19 December 1881</title>
            <title type="sub">TEI edition</title>
            <respStmt xml:lang="en">
               <resp>TEI edition</resp>
               <persName xml:id="pers_TG">Till Grallert</persName>
            </respStmt>
         </tei:titleStmt>
         <tei:publicationStmt>
            <authority>
               <persName>Till Grallert</persName>
            </authority>
            <pubPlace>Beirut</pubPlace>
            <date when="2018">2018</date>
            <availability status="restricted">
               <licence target="http://creativecommons.org/licenses/by-sa/4.0/">Distributed under a Creative Commons Attribution-ShareAlike 4.0 International (CC BY-SA 4.0) license</licence>
            </availability>
            <idno type="url">https://github.com/openarabicpe/newspaper_thamarat-al-funun/blob/master/xml/oclc_792755216-i_360.TEIP5.xml</idno>
         </tei:publicationStmt>
         <tei:sourceDesc>
            <tei:biblStruct xml:id="biblStruct_2.d1e40823" xml:lang="en">
                    <tei:monogr xml:id="monogr_2.d1e40825" xml:lang="en">
                        <title level="j" xml:id="title_2162.d1e40827" xml:lang="ar">ثمرات الفنون</title>
                        <title level="j" type="sub" xml:id="title_2163.d1e40830" xml:lang="ar">ان هذه الصحيفة تحتوي على حوادث سياسية ومحلية وتجارية وفنون</title>
                        <title level="j" type="sub" xml:id="title_2164.d1e40833" xml:lang="ar">صدورها في يوم الاثنين من كل اسبوع</title>
                        <title level="j" xml:id="title_2165.d1e40836" xml:lang="ar-Latn-x-ijmes">Thamarāt al-Funūn</title>
                        <title level="j"
                         type="sub"
                         xml:id="title_2166.d1e40839"
                         xml:lang="ar-Latn-x-ijmes">Inna hadhihi al-ṣaḥīfa taḥtawī ʿalā ḥawādith siyāsiyya wa-maḥalliyya wa-tijāriyya wa-funūn</title>
                        <title level="j"
                         type="sub"
                         xml:id="title_2167.d1e40843"
                         xml:lang="ar-Latn-x-ijmes">ṣudūruhā fī yawm al-ithnayn min kull usbūʿ</title>
                        <idno type="oclc" xml:id="idno_2161.d1e40846" xml:lang="en">792755216</idno>
                        <idno type="oclc" xml:id="idno_2162.d1e40849" xml:lang="en">745202659</idno>
                        <idno type="oclc" xml:id="idno_2163.d1e40852" xml:lang="en">915538205</idno>
                        <idno type="oclc" xml:id="idno_2164.d1e40855" xml:lang="en">30431084</idno>
                        <idno type="oclc" xml:id="idno_2165.d1e40858" xml:lang="en">499946128</idno>
                        <idno type="oclc" xml:id="idno_2166.d1e40862" xml:lang="en">177646790</idno>
                        <editor xml:id="editor_361.d1e40865" xml:lang="en">
                            <persName xml:id="persName_721.d1e40867" xml:lang="ar">
                                <forename xml:id="forename_721.d1e40869">عبد القادر</forename>
                                <surname xml:id="surname_721.d1e40872">قباني</surname>
                            </persName>
                            <persName xml:id="persName_722.d1e40876" xml:lang="ar-Latn-x-ijmes">
                                <forename xml:id="forename_722.d1e40878">ʿAbd al-Qādir</forename>
                                <surname xml:id="surname_722.d1e40881">Qabbānī</surname>
                            </persName>
                        </editor>
                        <tei:imprint xml:id="imprint_2.d1e40886" xml:lang="en">
                            <publisher xml:id="publisher_361.d1e40888" xml:lang="en">
                                <orgName xml:id="orgName_721.d1e40890" xml:lang="ar">مطبعة جمعية الفنون</orgName>
                                <orgName xml:id="orgName_722.d1e40893" xml:lang="ar-Latn-x-ijmes">Maṭbaʿa Jamʿiyyat al-Funūn</orgName>
                            </publisher>
                            <pubPlace xml:id="pubPlace_361.d1e40897" xml:lang="en">
                                <placeName xml:id="placeName_1441.d1e40899" xml:lang="ar">بيروت</placeName>
                                <placeName xml:id="placeName_1442.d1e40902" xml:lang="ar-Latn-x-ijmes">Bayrūt</placeName>
                                <placeName xml:id="placeName_1443.d1e40905" xml:lang="en">Beirut</placeName>
                                <placeName xml:id="placeName_1444.d1e40908" xml:lang="fr">Beyrouth</placeName>
                            </pubPlace>
                            <tei:date calendar="#cal_gregorian"
                               datingMethod="#cal_gregorian"
                               type="official"
                               when="1881-12-19"
                               xml:id="date_3.d1e40912"
                               xml:lang="ar-Latn-x-ijmes">19 December 1881</tei:date>
                            <tei:date calendar="#cal_islamic"
                               datingMethod="#cal_islamic"
                               type="computed"
                               when="1881-12-19"
                               when-custom="1299-01-27"
                               xml:id="date_3.d1e40915"
                               xml:lang="ar-Latn-x-ijmes">27 Muḥarram 1299</tei:date>
                            <tei:date calendar="#cal_julian"
                               datingMethod="#cal_julian"
                               type="official"
                               when="1881-12-19"
                               when-custom="1881-12-07"
                               xml:id="date_3.d1e40918"
                               xml:lang="ar-Latn-x-ijmes">7 Kānūn al-awwal 1881</tei:date>
                        </tei:imprint>
                        <tei:biblScope from="7" to="7" unit="volume" xml:id="biblScope_363.d1e40922"/>
                        <tei:biblScope from="360"
                                 to="360"
                                 unit="issue"
                                 xml:id="biblScope_363.d1e40924"/>
                        <biblScope from="1" to="4" unit="page" xml:id="biblScope_363.d1e40926"/>
                    </tei:monogr>
                    <note n="p_weekdays-published" type="param" xml:id="note_721.d1e40929">Monday</note>
                    <note n="p_step" type="param" xml:id="note_722.d1e40932">daily</note>
                </tei:biblStruct>
         </tei:sourceDesc>
      </tei:fileDesc>
      <tei:revisionDesc>
         <tei:change when="2018-07-04">Created this file by automatic conversion of <tei:gi>biblStruct</tei:gi> from file:/BachUni/BachBibliothek/GitHub/OpenArabicPE/newspaper_thamarat-al-funun/metadata/thamarat-al-funun.TEIP5.xml.</tei:change>
      </tei:revisionDesc>
   </tei:teiHeader>
   <tei:facsimile>
      <tei:surface xml:id="facs_1">
         <tei:graphic xml:id="facs_1-g_1"
                      url="../images/issues/oclc_792755216-i_360-p_1.jpg"
                      mimeType="image/jpeg"/>
      </tei:surface>
      <tei:surface xml:id="facs_2">
         <tei:graphic xml:id="facs_2-g_1"
                      url="../images/issues/oclc_792755216-i_360-p_2.jpg"
                      mimeType="image/jpeg"/>
      </tei:surface>
      <tei:surface xml:id="facs_3">
         <tei:graphic xml:id="facs_3-g_1"
                      url="../images/issues/oclc_792755216-i_360-p_3.jpg"
                      mimeType="image/jpeg"/>
      </tei:surface>
      <tei:surface xml:id="facs_4">
         <tei:graphic xml:id="facs_4-g_1"
                      url="../images/issues/oclc_792755216-i_360-p_4.jpg"
                      mimeType="image/jpeg"/>
      </tei:surface>
   </tei:facsimile>
   <tei:text xml:lang="ar">
      <tei:pb ed="print" n="1" facs="#facs_1"/>
      <tei:body>
         <tei:div type="item"/>
         <tei:pb ed="print" n="2" facs="#facs_2"/>
         <tei:pb ed="print" n="3" facs="#facs_3"/>
         <tei:pb ed="print" n="4" facs="#facs_4"/>
      </tei:body>
   </tei:text>
</tei:TEI>
