<?xml version="1.0" encoding="UTF-8"?><?xml-model href="https://rawgit.com/OpenArabicPE/OpenArabicPE_ODD/v0.1/schema/tei_periodical.rng" type="application/xml" schematypens="http://relaxng.org/ns/structure/1.0"?><?xml-stylesheet type="text/xsl" href="../xslt-boilerplate/teibp_parameters.xsl"?><tei:TEI xmlns:tei="http://www.tei-c.org/ns/1.0" xmlns="http://www.tei-c.org/ns/1.0" prev="oclc_792755216-i_404" next="oclc_792755216-i_406" xml:lang="">
   <tei:teiHeader xml:lang="en">
      <tei:fileDesc xml:lang="en">
         <tei:titleStmt xml:lang="en">
            <title xml:lang="en">Thamarāt al-Funūn #405, 4 December 1882</title>
            <title type="sub" xml:lang="en">TEI edition</title>
            <respStmt xml:lang="en">
               <resp xml:lang="en">TEI edition</resp>
               <persName xml:id="pers_TG" xml:lang="en">Till Grallert</persName>
            </respStmt>
         </tei:titleStmt>
         <tei:publicationStmt xml:lang="en">
            <authority xml:lang="en">
               <persName xml:lang="en">Till Grallert</persName>
            </authority>
            <pubPlace xml:lang="en">Beirut</pubPlace>
            <date when="2017" xml:lang="en">2017</date>
            <availability status="restricted" xml:lang="en">
               <licence target="http://creativecommons.org/licenses/by-sa/4.0/" xml:lang="en">Distributed under a Creative Commons Attribution-ShareAlike 4.0 International (CC BY-SA 4.0) license</licence>
            </availability>
            <idno type="url" xml:lang="en">https://github.com/openarabicpe/newspaper_thamarat-al-funun/blob/master/xml/oclc_792755216-i_405.TEIP5.xml</idno>
         </tei:publicationStmt>
         <tei:sourceDesc xml:lang="en">
            <tei:biblStruct xml:lang="en" xml:id="biblStruct_2.d1e45920">
               <tei:monogr xml:lang="en" xml:id="monogr_2.d1e45922">
                  <title level="j" xml:lang="ar" xml:id="title_2432.d1e45924">ثمرات الفنون</title>
                  <title level="j" type="sub" xml:lang="ar" xml:id="title_2433.d1e45927">ان هذه الصحيفة على حوادث سياسية ومحلية وتجارة وفنون</title>
                  <title level="j" type="sub" xml:lang="ar" xml:id="title_2434.d1e45930">صدورها في يوم الاثنين من كل اسبوع</title>
                  <title level="j" xml:lang="ar-Latn-x-ijmes" xml:id="title_2435.d1e45933">Thamarāt al-Funūn</title>
                  <title level="j" type="sub" xml:lang="ar-Latn-x-ijmes" xml:id="title_2436.d1e45936">Inna hadhihi al-ṣaḥīfa ʿalā ḥawādith siyāsiyya wa-maḥalliyya wa-tijāra wa-funūn</title>
                  <title level="j" type="sub" xml:lang="ar-Latn-x-ijmes" xml:id="title_2437.d1e45940">ṣudūruhā fī yawm al-ithnayn min kull usbūʿ</title>
                  <idno type="oclc" xml:lang="en" xml:id="idno_2431.d1e45943">792755216</idno>
                  <idno type="oclc" xml:lang="en" xml:id="idno_2432.d1e45946">745202659</idno>
                  <idno type="oclc" xml:lang="en" xml:id="idno_2433.d1e45949">915538205</idno>
                  <idno type="oclc" xml:lang="en" xml:id="idno_2434.d1e45952">30431084</idno>
                  <idno type="oclc" xml:lang="en" xml:id="idno_2435.d1e45955">499946128</idno>
                  <idno type="oclc" xml:lang="en" xml:id="idno_2436.d1e45959">177646790</idno>
                  <editor xml:lang="en" xml:id="editor_406.d1e45962"> 
                     <persName xml:lang="ar" xml:id="persName_811.d1e45964">
                            <forename xml:id="forename_811.d1e45966" xml:lang="ar">عبد القادر</forename> 
                        <surname xml:id="surname_811.d1e45969" xml:lang="ar">قباني</surname> 
                     </persName>
                            <persName xml:lang="ar-Latn-x-ijmes" xml:id="persName_812.d1e45973"> 
                        <forename xml:id="forename_812.d1e45975" xml:lang="ar-Latn-x-ijmes">ʿAbd al-Qādir</forename>
                            <surname xml:id="surname_812.d1e45978" xml:lang="ar-Latn-x-ijmes">Qabbānī</surname> 
                     </persName> 
                  </editor>
                  <tei:imprint xml:lang="en" xml:id="imprint_2.d1e45983">
                     <publisher xml:lang="en" xml:id="publisher_406.d1e45985"> 
                        <orgName xml:lang="ar" xml:id="orgName_811.d1e45987">مطبعة جمعية الفنون</orgName> 
                        <orgName xml:lang="ar-Latn-x-ijmes" xml:id="orgName_812.d1e45990">Maṭbaʿa Jamʿiyyat al-Funūn</orgName> 
                     </publisher>
                     <pubPlace xml:lang="en" xml:id="pubPlace_406.d1e45994"> 
                        <placeName xml:lang="ar" xml:id="placeName_1621.d1e45996">بيروت</placeName>
                                <placeName xml:lang="ar-Latn-x-ijmes" xml:id="placeName_1622.d1e45999">Bayrūt</placeName> 
                        <placeName xml:lang="en" xml:id="placeName_1623.d1e46002">Beirut</placeName> 
                        <placeName xml:lang="fr" xml:id="placeName_1624.d1e46005">Beyrouth</placeName> 
                     </pubPlace>
                     <tei:date type="official" when="1882-12-04" datingMethod="#cal_gregorian" calendar="#cal_gregorian" xml:lang="ar-Latn-x-ijmes" xml:id="date_3.d1e46009">4 December 1882</tei:date>
                     <tei:date type="computed" when="1882-12-04" datingMethod="#cal_islamic" calendar="#cal_islamic" when-custom="1300-01-23" xml:lang="ar-Latn-x-ijmes" xml:id="date_3.d1e46012">23 Muḥarram 1300</tei:date>
                     <tei:date type="official" when="1882-12-04" datingMethod="#cal_julian" calendar="#cal_julian" when-custom="1882-11-22" xml:lang="ar-Latn-x-ijmes" xml:id="date_3.d1e46015">22 Tishrīn al-thānī 1882</tei:date>
                  </tei:imprint>
                  <tei:biblScope from="8" to="8" unit="volume" xml:id="biblScope_408.d1e46019"/>
                  <tei:biblScope from="405" to="405" unit="issue" xml:id="biblScope_408.d1e46021"/>
                  <biblScope from="1" to="4" unit="page" xml:id="biblScope_408.d1e46023"/>
               </tei:monogr>
               <note n="p_weekdays-published" type="param" xml:id="note_811.d1e46026" xml:lang="en">Monday</note>
               <note n="p_step" type="param" xml:id="note_812.d1e46029" xml:lang="en">daily</note>
            </tei:biblStruct>
         </tei:sourceDesc>
      </tei:fileDesc>
      <tei:revisionDesc><tei:change when="2017-11-05" who="#pers_TG">Added the <tei:att>xml:lang</tei:att> attribute to all nodes that lacked this attribute. The value is based on the closest ancestor.</tei:change>
         <tei:change when="2017-11-05" xml:lang="en">Created this file by automatic conversion of <tei:gi xml:lang="en">biblStruct</tei:gi> from file:/Volumes/Dessau%20HD/BachUni/BachBibliothek/GitHub/OpenArabicPE/newspaper_thamarat-al-funun/tei/thamarat-al-funun.TEIP5.xml.</tei:change>
      </tei:revisionDesc>
   </tei:teiHeader>
   <tei:facsimile>
      <tei:surface xml:id="facs_1">
         <tei:graphic xml:id="facs_1-g_1" url="../images/issues/oclc_792755216-i_405-p_1.jpg" mimeType="image/jpeg"/>
         <tei:graphic xml:id="facs_1-g_2" url="../images/issues/oclc_792755216-i_405-p_1-color.jpg" mimeType="image/jpeg"/>
      </tei:surface>
      <tei:surface xml:id="facs_2">
         <tei:graphic xml:id="facs_2-g_1" url="../images/issues/oclc_792755216-i_405-p_2.jpg" mimeType="image/jpeg"/>
         <tei:graphic xml:id="facs_2-g_2" url="../images/issues/oclc_792755216-i_405-p_2-color.jpg" mimeType="image/jpeg"/>
      </tei:surface>
      <tei:surface xml:id="facs_3">
         <tei:graphic xml:id="facs_3-g_1" url="../images/issues/oclc_792755216-i_405-p_3.jpg" mimeType="image/jpeg"/>
         <tei:graphic xml:id="facs_3-g_2" url="../images/issues/oclc_792755216-i_405-p_3-color.jpg" mimeType="image/jpeg"/>
      </tei:surface>
      <tei:surface xml:id="facs_4">
         <tei:graphic xml:id="facs_4-g_1" url="../images/issues/oclc_792755216-i_405-p_4.jpg" mimeType="image/jpeg"/>
         <tei:graphic xml:id="facs_4-g_2" url="../images/issues/oclc_792755216-i_405-p_4-color.jpg" mimeType="image/jpeg"/>
      </tei:surface>
   </tei:facsimile>
   <tei:text xml:lang="ar">
      <tei:pb ed="print" n="1" facs="#facs_1"/>
      <tei:body xml:lang="ar">
         <tei:pb ed="print" n="2" facs="#facs_2"/>
         <tei:pb ed="print" n="3" facs="#facs_3"/>
         <tei:pb ed="print" n="4" facs="#facs_4"/>
      </tei:body>
   </tei:text>
</tei:TEI>