<?xml version="1.0" encoding="UTF-8"?><?xml-model href="https://rawgit.com/OpenArabicPE/OpenArabicPE_ODD/v0.1/schema/tei_periodical.rng" type="application/xml" schematypens="http://relaxng.org/ns/structure/1.0"?><?xml-stylesheet type="text/xsl" href="../boilerplate/xslt/teibp_parameters.xsl"?><tei:TEI xmlns:tei="http://www.tei-c.org/ns/1.0"
         xmlns="http://www.tei-c.org/ns/1.0"
         xml:id="oclc_792755216-i_253"
         prev="oclc_792755216-i_252.TEIP5.xml"
         next="oclc_792755216-i_254.TEIP5.xml">
   <tei:teiHeader xml:lang="en">
      <tei:fileDesc>
         <tei:titleStmt>
            <title>Thamarāt al-Funūn #253, 3 November 1879</title>
            <title type="sub">TEI edition</title>
            <respStmt xml:lang="en">
               <resp>TEI edition</resp>
               <persName xml:id="pers_TG">Till Grallert</persName>
            </respStmt>
         </tei:titleStmt>
         <tei:publicationStmt>
            <authority>
               <persName>Till Grallert</persName>
            </authority>
            <pubPlace>Beirut</pubPlace>
            <date when="2018">2018</date>
            <availability status="restricted">
               <licence target="http://creativecommons.org/licenses/by-sa/4.0/">Distributed under a Creative Commons Attribution-ShareAlike 4.0 International (CC BY-SA 4.0) license</licence>
            </availability>
            <idno type="url">https://github.com/openarabicpe/newspaper_thamarat-al-funun/blob/master/xml/oclc_792755216-i_253.TEIP5.xml</idno>
         </tei:publicationStmt>
         <tei:sourceDesc>
            <tei:biblStruct xml:id="biblStruct_2.d1e28693" xml:lang="en">
               <tei:monogr xml:id="monogr_2.d1e28695" xml:lang="en">
                  <title level="j" xml:id="title_1520.d1e28697" xml:lang="ar">ثمرات الفنون</title>
                  <title level="j" type="sub" xml:id="title_1521.d1e28700" xml:lang="ar">ان هذه الصحيفة تحتوي على حوادث سياسية ومحلية وتجارة وفنون</title>
                  <title level="j" type="sub" xml:id="title_1522.d1e28703" xml:lang="ar">صدورها في يوم الاثنين من كل اسبوع</title>
                  <title level="j" xml:id="title_1523.d1e28706" xml:lang="ar-Latn-x-ijmes">Thamarāt al-Funūn</title>
                  <title level="j"
                         type="sub"
                         xml:id="title_1524.d1e28709"
                         xml:lang="ar-Latn-x-ijmes">Inna hadhihi al-ṣaḥīfa taḥtawī ʿalā ḥawādith siyāsiyya wa-maḥalliyya wa-tijāra wa-funūn</title>
                  <title level="j"
                         type="sub"
                         xml:id="title_1525.d1e28713"
                         xml:lang="ar-Latn-x-ijmes">ṣudūruhā fī yawm al-ithnayn min kull usbūʿ</title>
                  <idno type="oclc" xml:id="idno_1519.d1e28716" xml:lang="en">792755216</idno>
                  <idno type="oclc" xml:id="idno_1520.d1e28719" xml:lang="en">745202659</idno>
                  <idno type="oclc" xml:id="idno_1521.d1e28722" xml:lang="en">915538205</idno>
                  <idno type="oclc" xml:id="idno_1522.d1e28725" xml:lang="en">30431084</idno>
                  <idno type="oclc" xml:id="idno_1523.d1e28728" xml:lang="en">499946128</idno>
                  <idno type="oclc" xml:id="idno_1524.d1e28732" xml:lang="en">177646790</idno>
                  <editor xml:id="editor_254.d1e28735" xml:lang="en">
                     <persName xml:id="persName_507.d1e28737" xml:lang="ar">
                        <forename xml:id="forename_507.d1e28739">عبد القادر</forename>
                        <surname xml:id="surname_507.d1e28742">قباني</surname>
                     </persName>
                     <persName xml:id="persName_508.d1e28746" xml:lang="ar-Latn-x-ijmes">
                        <forename xml:id="forename_508.d1e28748">ʿAbd al-Qādir</forename>
                        <surname xml:id="surname_508.d1e28751">Qabbānī</surname>
                     </persName>
                  </editor>
                  <tei:imprint xml:id="imprint_2.d1e28756" xml:lang="en">
                     <publisher xml:id="publisher_254.d1e28758" xml:lang="en">
                        <orgName xml:id="orgName_507.d1e28760" xml:lang="ar">مطبعة جمعية الفنون</orgName>
                        <orgName xml:id="orgName_508.d1e28763" xml:lang="ar-Latn-x-ijmes">Maṭbaʿa Jamʿiyyat al-Funūn</orgName>
                     </publisher>
                     <pubPlace xml:id="pubPlace_254.d1e28767" xml:lang="en">
                        <placeName xml:id="placeName_1013.d1e28769" xml:lang="ar">بيروت</placeName>
                        <placeName xml:id="placeName_1014.d1e28772" xml:lang="ar-Latn-x-ijmes">Bayrūt</placeName>
                        <placeName xml:id="placeName_1015.d1e28775" xml:lang="en">Beirut</placeName>
                        <placeName xml:id="placeName_1016.d1e28778" xml:lang="fr">Beyrouth</placeName>
                     </pubPlace>
                     <tei:date calendar="#cal_gregorian"
                               datingMethod="#cal_gregorian"
                               type="official"
                               when="1879-11-03"
                               xml:id="date_3.d1e28782"
                               xml:lang="ar-Latn-x-ijmes">3 November 1879</tei:date>
                     <tei:date calendar="#cal_islamic"
                               datingMethod="#cal_islamic"
                               type="computed"
                               when="1879-11-03"
                               when-custom="1296-11-18"
                               xml:id="date_3.d1e28785"
                               xml:lang="ar-Latn-x-ijmes">18 Dhū al-qaʿda 1296</tei:date>
                     <tei:date calendar="#cal_julian"
                               datingMethod="#cal_julian"
                               type="official"
                               when="1879-11-03"
                               when-custom="1879-10-22"
                               xml:id="date_3.d1e28788"
                               xml:lang="ar-Latn-x-ijmes">22 Tishrīn al-awwal 1879</tei:date>
                  </tei:imprint>
                  <tei:biblScope from="5" to="5" unit="volume" xml:id="biblScope_256.d1e28792"/>
                  <tei:biblScope from="253"
                                 to="253"
                                 unit="issue"
                                 xml:id="biblScope_256.d1e28794"/>
                  <biblScope from="1" to="4" unit="page" xml:id="biblScope_256.d1e28796"/>
               </tei:monogr>
               <note n="p_weekdays-published" type="param" xml:id="note_507.d1e28799">Monday</note>
               <note n="p_step" type="param" xml:id="note_508.d1e28802">daily</note>
            </tei:biblStruct>
         </tei:sourceDesc>
      </tei:fileDesc>
      <tei:revisionDesc>
         <tei:change when="2018-01-07">Created this file by automatic conversion of <tei:gi>biblStruct</tei:gi> from file:/Volumes/Dessau%20HD/BachUni/BachBibliothek/GitHub/OpenArabicPE/newspaper_thamarat-al-funun/metadata/thamarat-al-funun.TEIP5.xml.</tei:change>
      </tei:revisionDesc>
   </tei:teiHeader>
   <tei:facsimile>
      <tei:surface xml:id="facs_1">
         <tei:graphic xml:id="facs_1-g_1"
                      url="../images/issues/oclc_792755216-i_253-p_1.jpg"
                      mimeType="image/jpeg"/>
      </tei:surface>
      <tei:surface xml:id="facs_2">
         <tei:graphic xml:id="facs_2-g_1"
                      url="../images/issues/oclc_792755216-i_253-p_2.jpg"
                      mimeType="image/jpeg"/>
      </tei:surface>
      <tei:surface xml:id="facs_3">
         <tei:graphic xml:id="facs_3-g_1"
                      url="../images/issues/oclc_792755216-i_253-p_3.jpg"
                      mimeType="image/jpeg"/>
      </tei:surface>
      <tei:surface xml:id="facs_4">
         <tei:graphic xml:id="facs_4-g_1"
                      url="../images/issues/oclc_792755216-i_253-p_4.jpg"
                      mimeType="image/jpeg"/>
      </tei:surface>
   </tei:facsimile>
   <tei:text xml:lang="ar">
      <tei:pb ed="print" n="1" facs="#facs_1"/>
      <tei:body>
         <tei:pb ed="print" n="2" facs="#facs_2"/>
         <tei:pb ed="print" n="3" facs="#facs_3"/>
         <tei:pb ed="print" n="4" facs="#facs_4"/>
      </tei:body>
   </tei:text>
</tei:TEI>
